setup.py
except_py_client/__init__.py
except_py_client/client.py
except_py_client.egg-info/PKG-INFO
except_py_client.egg-info/SOURCES.txt
except_py_client.egg-info/dependency_links.txt
except_py_client.egg-info/requires.txt
except_py_client.egg-info/top_level.txt
except_py_client/django/__init__.py