Metadata-Version: 1.0
Name: except-py-client
Version: 0.1.2
Summary: except.py client library
Home-page: UNKNOWN
Author: Viktor Kotseruba
Author-email: barbuzaster@gmail.com
License: MIT
Keywords: exceptions logging errors
Platform: UNKNOWN
